metathethaurus_client/__init__.py
metathethaurus_client_timoderbeste-0.0.1.dist-info/METADATA
metathethaurus_client_timoderbeste-0.0.1.dist-info/WHEEL
metathethaurus_client_timoderbeste-0.0.1.dist-info/top_level.txt
metathethaurus_client_timoderbeste-0.0.1.dist-info/RECORD
