Metadata-Version: 2.1
Name: metathethaurus-client-timoderbeste
Version: 0.0.1
Summary: A small client for interacting with metathethaurs apis
Home-page: UNKNOWN
Author: Timo Wang
Author-email: ntwang1994@gmail.com
License: UNKNOWN
Platform: UNKNOWN
Classifier: Programming Language :: Python :: 3
Classifier: License :: OSI Approved :: MIT License
Classifier: Operating System :: OS Independent
Requires-Python: >=3.6
